<?xml version="1.0" encoding="utf-8" ?>
<dwsync>
<file name="Btn_EVENTS.png" server="dreamingsideways.com" local="130907032200000000" remote="130907032200000000" Dst="2" />
<file name="Btn_HOME.png" server="dreamingsideways.com" local="130907032200000000" remote="130907032200000000" Dst="2" />
<file name="Btn_MATCH.png" server="dreamingsideways.com" local="130996359000000000" remote="130996359000000000" Dst="2" />
<file name="Btn_NEWS.png" server="dreamingsideways.com" local="130907032200000000" remote="130907032200000000" Dst="2" />
<file name="Btn_STORE.png" server="dreamingsideways.com" local="130996359000000000" remote="130996359000000000" Dst="2" />
<file name="Btn_LOGIN.png" server="dreamingsideways.com" local="130907032200000000" remote="130907032200000000" Dst="2" />
<file name="Btn_REGISTER.png" server="dreamingsideways.com" local="130907032200000000" remote="130907032200000000" Dst="2" />
<file name="Top Bar Button Maker.png" server="dreamingsideways.com" local="130837392000000000" remote="130837392000000000" Dst="2" />
</dwsync>